[{"id": "c8301213-ae5b-4a3b-9c0b-4d3953ccc36b", "data": [{"text": "Can I find ", "userDefined": false}, {"text": "CSC 203", "userDefined": false, "alias": "CLASS_NAME", "meta": "@CLASS_NAME"}, {"text": " listed in another department?", "userDefined": false}], "count": 0, "isTemplate": false}, {"id": "7d88fbb0-3d06-484f-971b-f55bba0f611c", "data": [{"text": "Can I find ", "userDefined": false}, {"text": "fundamentals-of computer science-for scientists-and engineers ii", "userDefined": false, "alias": "CLASS_NAME", "meta": "@CLASS_NAME"}, {"text": " listed in another department?", "userDefined": false}], "count": 0, "isTemplate": false}, {"id": "bda89796-3712-448f-b69b-95389dde8a29", "data": [{"text": "Can I find ", "userDefined": false}, {"text": "introduction-to operating systems", "userDefined": false, "alias": "CLASS_NAME", "meta": "@CLASS_NAME"}, {"text": " listed in another department?", "userDefined": false}], "count": 0, "isTemplate": false}, {"id": "e7d05474-82a1-4791-a862-6a9bf96b9918", "data": [{"text": "Can I find ", "userDefined": false}, {"text": "CSC 596", "userDefined": false, "alias": "CLASS_NAME", "meta": "@CLASS_NAME"}, {"text": " listed in another department?", "userDefined": false}], "count": 0, "isTemplate": false}, {"id": "2fd1d1de-0a75-40dd-af0a-17c2b299552f", "data": [{"text": "Can I find ", "userDefined": false}, {"text": "computing-for interactive arts capstone ii", "userDefined": false, "alias": "CLASS_NAME", "meta": "@CLASS_NAME"}, {"text": " listed in another department?", "userDefined": false}], "count": 0, "isTemplate": false}, {"id": "1fac8a96-588e-4ee5-9b27-4e41c212ee13", "data": [{"text": "Can I find ", "userDefined": false}, {"text": "CSC 410", "userDefined": false, "alias": "CLASS_NAME", "meta": "@CLASS_NAME"}, {"text": " listed in another department?", "userDefined": false}], "count": 0, "isTemplate": false}, {"id": "10999f9f-6b01-4e27-ba85-147d862b6876", "data": [{"text": "Can I find ", "userDefined": false}, {"text": "cooperative education experience", "userDefined": false, "alias": "CLASS_NAME", "meta": "@CLASS_NAME"}, {"text": " listed in another department?", "userDefined": false}], "count": 0, "isTemplate": false}, {"id": "a9fe840a-dfe7-4b81-84a5-7063a4511bfb", "data": [{"text": "Can I find ", "userDefined": false}, {"text": "CSC 108", "userDefined": false, "alias": "CLASS_NAME", "meta": "@CLASS_NAME"}, {"text": " listed in another department?", "userDefined": false}], "count": 0, "isTemplate": false}, {"id": "32977be3-81a6-45f1-8ea7-97a863576683", "data": [{"text": "Can I find ", "userDefined": false}, {"text": "CSC 468", "userDefined": false, "alias": "CLASS_NAME", "meta": "@CLASS_NAME"}, {"text": " listed in another department?", "userDefined": false}], "count": 0, "isTemplate": false}, {"id": "67e9cbb4-39fd-4d9a-b339-d90ed603e359", "data": [{"text": "Can I find ", "userDefined": false}, {"text": "CSC 458", "userDefined": false, "alias": "CLASS_NAME", "meta": "@CLASS_NAME"}, {"text": " listed in another department?", "userDefined": false}], "count": 0, "isTemplate": false}, {"id": "b8205b45-cfd6-4c16-b3ea-f0e740165c36", "data": [{"text": "Is there another department listing of ", "userDefined": false}, {"text": "CSC 350", "userDefined": false, "alias": "CLASS_NAME", "meta": "@CLASS_NAME"}, {"text": "?", "userDefined": false}], "count": 0, "isTemplate": false}, {"id": "5aaad0f1-a6cc-4341-b40d-2f84880877ba", "data": [{"text": "Is there another department listing of ", "userDefined": false}, {"text": "CSC 236", "userDefined": false, "alias": "CLASS_NAME", "meta": "@CLASS_NAME"}, {"text": "?", "userDefined": false}], "count": 0, "isTemplate": false}, {"id": "85a726b2-c835-4e93-8d1f-dfe1fb9f42b8", "data": [{"text": "Is there another department listing of ", "userDefined": false}, {"text": "CSC 478", "userDefined": false, "alias": "CLASS_NAME", "meta": "@CLASS_NAME"}, {"text": "?", "userDefined": false}], "count": 0, "isTemplate": false}, {"id": "57eec37b-d4ae-487d-933a-595fccd4e65c", "data": [{"text": "Is there another department listing of ", "userDefined": false}, {"text": "CSC 508", "userDefined": false, "alias": "CLASS_NAME", "meta": "@CLASS_NAME"}, {"text": "?", "userDefined": false}], "count": 0, "isTemplate": false}, {"id": "d956ee72-8615-4b23-b5d8-aca6e01c7d89", "data": [{"text": "Is there another department listing of ", "userDefined": false}, {"text": "research-in computer science i", "userDefined": false, "alias": "CLASS_NAME", "meta": "@CLASS_NAME"}, {"text": "?", "userDefined": false}], "count": 0, "isTemplate": false}, {"id": "8cf81915-932e-41d2-9045-548e7e40b419", "data": [{"text": "Is there another department listing of ", "userDefined": false}, {"text": "special problems", "userDefined": false, "alias": "CLASS_NAME", "meta": "@CLASS_NAME"}, {"text": "?", "userDefined": false}], "count": 0, "isTemplate": false}, {"id": "7895f7f4-3af6-4539-8190-13aa7bca552b", "data": [{"text": "Is there another department listing of ", "userDefined": false}, {"text": "CSC 308", "userDefined": false, "alias": "CLASS_NAME", "meta": "@CLASS_NAME"}, {"text": "?", "userDefined": false}], "count": 0, "isTemplate": false}, {"id": "a2b955dd-bf5a-4e19-ab1c-97ac0cf5ac83", "data": [{"text": "Is there another department listing of ", "userDefined": false}, {"text": "CSC 310", "userDefined": false, "alias": "CLASS_NAME", "meta": "@CLASS_NAME"}, {"text": "?", "userDefined": false}], "count": 0, "isTemplate": false}, {"id": "11f0f6b7-f43a-4383-b316-0ee8d3138aaa", "data": [{"text": "Is there another department listing of ", "userDefined": false}, {"text": "database management systems implementation", "userDefined": false, "alias": "CLASS_NAME", "meta": "@CLASS_NAME"}, {"text": "?", "userDefined": false}], "count": 0, "isTemplate": false}, {"id": "7fd95e15-ded7-4ad6-a21c-53090a2d033e", "data": [{"text": "Is there another department listing of ", "userDefined": false}, {"text": "fundamentals-of computer science-for scientists-and engineers ii", "userDefined": false, "alias": "CLASS_NAME", "meta": "@CLASS_NAME"}, {"text": "?", "userDefined": false}], "count": 0, "isTemplate": false}, {"id": "ad97a8db-2985-44dc-88ff-4ad97e241bf5", "data": [{"text": "Is ", "userDefined": false}, {"text": "advanced rendering techniques", "userDefined": false, "alias": "CLASS_NAME", "meta": "@CLASS_NAME"}, {"text": " crosslisted somewhere else?", "userDefined": false}], "count": 0, "isTemplate": false}, {"id": "7c3bc9f6-f2aa-4f6f-946a-94420185f2d9", "data": [{"text": "Is ", "userDefined": false}, {"text": "CSC 209", "userDefined": false, "alias": "CLASS_NAME", "meta": "@CLASS_NAME"}, {"text": " crosslisted somewhere else?", "userDefined": false}], "count": 0, "isTemplate": false}, {"id": "f9f1a825-2e67-4394-b09f-e0d51b9b8e4b", "data": [{"text": "Is ", "userDefined": false}, {"text": "CSC 300", "userDefined": false, "alias": "CLASS_NAME", "meta": "@CLASS_NAME"}, {"text": " crosslisted somewhere else?", "userDefined": false}], "count": 0, "isTemplate": false}, {"id": "6a2d47dd-b883-48dc-b3bc-f72691a37235", "data": [{"text": "Is ", "userDefined": false}, {"text": "current topics-in human-computer interaction", "userDefined": false, "alias": "CLASS_NAME", "meta": "@CLASS_NAME"}, {"text": " crosslisted somewhere else?", "userDefined": false}], "count": 0, "isTemplate": false}, {"id": "28dce992-c16f-4ee3-8d6b-ec6aa965ea29", "data": [{"text": "Is ", "userDefined": false}, {"text": "cooperative education experience", "userDefined": false, "alias": "CLASS_NAME", "meta": "@CLASS_NAME"}, {"text": " crosslisted somewhere else?", "userDefined": false}], "count": 0, "isTemplate": false}, {"id": "c79524ae-1b57-4a08-bed7-de692b495f2e", "data": [{"text": "Is ", "userDefined": false}, {"text": "CSC 521", "userDefined": false, "alias": "CLASS_NAME", "meta": "@CLASS_NAME"}, {"text": " crosslisted somewhere else?", "userDefined": false}], "count": 0, "isTemplate": false}, {"id": "6b1d818f-8d5b-4b5d-9f76-12110a6d1601", "data": [{"text": "Is ", "userDefined": false}, {"text": "CSC 310", "userDefined": false, "alias": "CLASS_NAME", "meta": "@CLASS_NAME"}, {"text": " crosslisted somewhere else?", "userDefined": false}], "count": 0, "isTemplate": false}, {"id": "02690ac2-f4d8-4d2c-9d5d-40b229e02857", "data": [{"text": "Is ", "userDefined": false}, {"text": "CSC 466", "userDefined": false, "alias": "CLASS_NAME", "meta": "@CLASS_NAME"}, {"text": " crosslisted somewhere else?", "userDefined": false}], "count": 0, "isTemplate": false}, {"id": "a92be80c-46ed-4578-b0d3-36f2a1e63b33", "data": [{"text": "Is ", "userDefined": false}, {"text": "music programming", "userDefined": false, "alias": "CLASS_NAME", "meta": "@CLASS_NAME"}, {"text": " crosslisted somewhere else?", "userDefined": false}], "count": 0, "isTemplate": false}, {"id": "4b332787-1748-473d-be84-65035ede4d50", "data": [{"text": "Is ", "userDefined": false}, {"text": "CSC 310", "userDefined": false, "alias": "CLASS_NAME", "meta": "@CLASS_NAME"}, {"text": " crosslisted somewhere else?", "userDefined": false}], "count": 0, "isTemplate": false}, {"id": "8bcb681c-de58-4ba3-8dee-f0ea33d5823b", "data": [{"text": "Is ", "userDefined": false}, {"text": "network-and web security", "userDefined": false, "alias": "CLASS_NAME", "meta": "@CLASS_NAME"}, {"text": " crosslisted in some other department?", "userDefined": false}], "count": 0, "isTemplate": false}, {"id": "9ef72969-b50b-47e4-9ca8-93313e3d4ea5", "data": [{"text": "Is ", "userDefined": false}, {"text": "CSC 402", "userDefined": false, "alias": "CLASS_NAME", "meta": "@CLASS_NAME"}, {"text": " crosslisted in some other department?", "userDefined": false}], "count": 0, "isTemplate": false}, {"id": "0d4c3cc7-0c4f-4cf3-bbf3-e723d606073e", "data": [{"text": "Is ", "userDefined": false}, {"text": "special problems", "userDefined": false, "alias": "CLASS_NAME", "meta": "@CLASS_NAME"}, {"text": " crosslisted in some other department?", "userDefined": false}], "count": 0, "isTemplate": false}, {"id": "ae38a439-eedb-4dac-81cf-c0da994eb969", "data": [{"text": "Is ", "userDefined": false}, {"text": "CSC 445", "userDefined": false, "alias": "CLASS_NAME", "meta": "@CLASS_NAME"}, {"text": " crosslisted in some other department?", "userDefined": false}], "count": 0, "isTemplate": false}, {"id": "10dbe29d-0d74-4ff1-9bf6-ea4bb2798311", "data": [{"text": "Is ", "userDefined": false}, {"text": "distributed computing", "userDefined": false, "alias": "CLASS_NAME", "meta": "@CLASS_NAME"}, {"text": " crosslisted in some other department?", "userDefined": false}], "count": 0, "isTemplate": false}, {"id": "f169c03e-c7ac-4fa4-b95d-91690dfa86a6", "data": [{"text": "Is ", "userDefined": false}, {"text": "CSC 582", "userDefined": false, "alias": "CLASS_NAME", "meta": "@CLASS_NAME"}, {"text": " crosslisted in some other department?", "userDefined": false}], "count": 0, "isTemplate": false}, {"id": "e52db32b-848e-4c05-875f-08be60404b21", "data": [{"text": "Is ", "userDefined": false}, {"text": "CSC 108", "userDefined": false, "alias": "CLASS_NAME", "meta": "@CLASS_NAME"}, {"text": " crosslisted in some other department?", "userDefined": false}], "count": 0, "isTemplate": false}, {"id": "d022b4dc-5e78-4adc-b4dd-1769a4b3442f", "data": [{"text": "Is ", "userDefined": false}, {"text": "CSC 469", "userDefined": false, "alias": "CLASS_NAME", "meta": "@CLASS_NAME"}, {"text": " crosslisted in some other department?", "userDefined": false}], "count": 0, "isTemplate": false}, {"id": "3808c9f2-48d2-4e0f-b870-a00a3d472eab", "data": [{"text": "Is ", "userDefined": false}, {"text": "operating systems", "userDefined": false, "alias": "CLASS_NAME", "meta": "@CLASS_NAME"}, {"text": " crosslisted in some other department?", "userDefined": false}], "count": 0, "isTemplate": false}, {"id": "fa986611-00c2-484a-9871-493c72da84be", "data": [{"text": "Is ", "userDefined": false}, {"text": "CSC 486", "userDefined": false, "alias": "CLASS_NAME", "meta": "@CLASS_NAME"}, {"text": " crosslisted in some other department?", "userDefined": false}], "count": 0, "isTemplate": false}, {"id": "f4b12272-47a7-4395-acbe-7db3b46f8cfe", "data": [{"text": "Is ", "userDefined": false}, {"text": "computer networks: research topics", "userDefined": false, "alias": "CLASS_NAME", "meta": "@CLASS_NAME"}, {"text": " crosslisted?", "userDefined": false}], "count": 0, "isTemplate": false}, {"id": "21b41349-8826-41e8-b450-46a7921416b9", "data": [{"text": "Is ", "userDefined": false}, {"text": "CSC 234", "userDefined": false, "alias": "CLASS_NAME", "meta": "@CLASS_NAME"}, {"text": " crosslisted?", "userDefined": false}], "count": 0, "isTemplate": false}, {"id": "0a2fc828-321c-41b7-9427-4338cad404eb", "data": [{"text": "Is ", "userDefined": false}, {"text": "programming languages", "userDefined": false, "alias": "CLASS_NAME", "meta": "@CLASS_NAME"}, {"text": " crosslisted?", "userDefined": false}], "count": 0, "isTemplate": false}, {"id": "17717bf3-c9ae-4422-95fc-3e2d3b9f18e1", "data": [{"text": "Is ", "userDefined": false}, {"text": "CSC 200", "userDefined": false, "alias": "CLASS_NAME", "meta": "@CLASS_NAME"}, {"text": " crosslisted?", "userDefined": false}], "count": 0, "isTemplate": false}, {"id": "02a07cf3-b425-42fc-869c-a282102fc7c1", "data": [{"text": "Is ", "userDefined": false}, {"text": "introduction-to object oriented design using graphical user interfaces", "userDefined": false, "alias": "CLASS_NAME", "meta": "@CLASS_NAME"}, {"text": " crosslisted?", "userDefined": false}], "count": 0, "isTemplate": false}, {"id": "4faf0135-10b4-4411-9184-1cf52b5f3ac6", "data": [{"text": "Is ", "userDefined": false}, {"text": "CSC 409", "userDefined": false, "alias": "CLASS_NAME", "meta": "@CLASS_NAME"}, {"text": " crosslisted?", "userDefined": false}], "count": 0, "isTemplate": false}, {"id": "7bd7c869-dbbd-4270-872b-fef0477058c4", "data": [{"text": "Is ", "userDefined": false}, {"text": "CSC 482", "userDefined": false, "alias": "CLASS_NAME", "meta": "@CLASS_NAME"}, {"text": " crosslisted?", "userDefined": false}], "count": 0, "isTemplate": false}, {"id": "28519fe1-6b52-48c4-a13c-3c4415c052be", "data": [{"text": "Is ", "userDefined": false}, {"text": "fundamentals-of computer science-for scientists-and engineers i", "userDefined": false, "alias": "CLASS_NAME", "meta": "@CLASS_NAME"}, {"text": " crosslisted?", "userDefined": false}], "count": 0, "isTemplate": false}, {"id": "e8e6907e-1814-4d46-bfcf-01bece553894", "data": [{"text": "Is ", "userDefined": false}, {"text": "CSC 236", "userDefined": false, "alias": "CLASS_NAME", "meta": "@CLASS_NAME"}, {"text": " crosslisted?", "userDefined": false}], "count": 0, "isTemplate": false}, {"id": "4b7956ad-27f6-4ba0-a448-6a9f7fe5ef42", "data": [{"text": "Is ", "userDefined": false}, {"text": "current topics-in software engineering", "userDefined": false, "alias": "CLASS_NAME", "meta": "@CLASS_NAME"}, {"text": " crosslisted?", "userDefined": false}], "count": 0, "isTemplate": false}, {"id": "5c9415ed-8623-434f-b099-3cf16d237071", "data": [{"text": "Is ", "userDefined": false}, {"text": "CSC 597", "userDefined": false, "alias": "CLASS_NAME", "meta": "@CLASS_NAME"}, {"text": " crosslisted in another department?", "userDefined": false}], "count": 0, "isTemplate": false}, {"id": "76298f24-5e8e-4713-941e-ab3247af5038", "data": [{"text": "Is ", "userDefined": false}, {"text": "human-computer interaction theory-and design", "userDefined": false, "alias": "CLASS_NAME", "meta": "@CLASS_NAME"}, {"text": " crosslisted in another department?", "userDefined": false}], "count": 0, "isTemplate": false}, {"id": "316e949b-cf6e-4f98-bba8-98ae1d960c36", "data": [{"text": "Is ", "userDefined": false}, {"text": "CSC 596", "userDefined": false, "alias": "CLASS_NAME", "meta": "@CLASS_NAME"}, {"text": " crosslisted in another department?", "userDefined": false}], "count": 0, "isTemplate": false}, {"id": "5d483aee-f8d6-4e76-9b8c-0df109160ef0", "data": [{"text": "Is ", "userDefined": false}, {"text": "CSC 477", "userDefined": false, "alias": "CLASS_NAME", "meta": "@CLASS_NAME"}, {"text": " crosslisted in another department?", "userDefined": false}], "count": 0, "isTemplate": false}, {"id": "bdac9bbc-ff2f-4dde-8842-8d15d5519dc3", "data": [{"text": "Is ", "userDefined": false}, {"text": "senior project ii", "userDefined": false, "alias": "CLASS_NAME", "meta": "@CLASS_NAME"}, {"text": " crosslisted in another department?", "userDefined": false}], "count": 0, "isTemplate": false}, {"id": "2ded0ccd-580c-449e-ad48-e9e61ac04b89", "data": [{"text": "Is ", "userDefined": false}, {"text": "CSC 515", "userDefined": false, "alias": "CLASS_NAME", "meta": "@CLASS_NAME"}, {"text": " crosslisted in another department?", "userDefined": false}], "count": 0, "isTemplate": false}, {"id": "fc31f393-63bd-4d0e-9eef-959d46d693a8", "data": [{"text": "Is ", "userDefined": false}, {"text": "practical computer security-for everyone", "userDefined": false, "alias": "CLASS_NAME", "meta": "@CLASS_NAME"}, {"text": " crosslisted in another department?", "userDefined": false}], "count": 0, "isTemplate": false}, {"id": "91f36b46-1a14-4a86-b4bb-99e680416df3", "data": [{"text": "Is ", "userDefined": false}, {"text": "CSC 478", "userDefined": false, "alias": "CLASS_NAME", "meta": "@CLASS_NAME"}, {"text": " crosslisted in another department?", "userDefined": false}], "count": 0, "isTemplate": false}, {"id": "3a2e05ed-d353-4e8c-bd82-9e6e0f69c49b", "data": [{"text": "Is ", "userDefined": false}, {"text": "research-in computer science i", "userDefined": false, "alias": "CLASS_NAME", "meta": "@CLASS_NAME"}, {"text": " crosslisted in another department?", "userDefined": false}], "count": 0, "isTemplate": false}, {"id": "d31b870b-7958-480d-a076-b36f46863db0", "data": [{"text": "Is ", "userDefined": false}, {"text": "CSC 429", "userDefined": false, "alias": "CLASS_NAME", "meta": "@CLASS_NAME"}, {"text": " crosslisted in another department?", "userDefined": false}], "count": 0, "isTemplate": false}]