[{"data": [{"userDefined": false, "text": "Which courses are seminars?"}], "isTemplate": false, "id": "bdd4e109-e877-40e3-b110-88896144046e", "count": 0}, {"data": [{"userDefined": false, "text": "Which courses are seminars?"}], "isTemplate": false, "id": "f8104beb-1659-42fa-8ca7-231448dc2bd1", "count": 0}, {"data": [{"userDefined": false, "text": "Which courses are seminars?"}], "isTemplate": false, "id": "154a28d9-74b5-4861-90e7-d22d8b358b11", "count": 0}, {"data": [{"userDefined": false, "text": "Which courses are seminars?"}], "isTemplate": false, "id": "0972be39-3be2-47d1-bd87-630e4bb1cad4", "count": 0}, {"data": [{"userDefined": false, "text": "Which courses are seminars?"}], "isTemplate": false, "id": "e91761d8-0d0d-4232-9d6c-3308d590323e", "count": 0}, {"data": [{"userDefined": false, "text": "Which courses are seminars?"}], "isTemplate": false, "id": "c2756cc3-dee2-4737-ad96-749ae638ef61", "count": 0}, {"data": [{"userDefined": false, "text": "Which courses are seminars?"}], "isTemplate": false, "id": "c883f753-02e4-434a-a389-e6cd145e93ea", "count": 0}, {"data": [{"userDefined": false, "text": "Which courses are seminars?"}], "isTemplate": false, "id": "01caaab4-a277-4d22-b1e9-ce60de8bbb76", "count": 0}, {"data": [{"userDefined": false, "text": "Which courses are seminars?"}], "isTemplate": false, "id": "a8330d59-dc79-407d-ad27-7552d7ae515e", "count": 0}, {"data": [{"userDefined": false, "text": "Which courses are seminars?"}], "isTemplate": false, "id": "731de121-1759-4625-82ae-2228e018c957", "count": 0}, {"data": [{"userDefined": false, "text": "What classes are considered to be seminars?"}], "isTemplate": false, "id": "9a237301-4b31-472a-b60c-fdaadf15960c", "count": 0}, {"data": [{"userDefined": false, "text": "What classes are considered to be seminars?"}], "isTemplate": false, "id": "912ecdb9-b02a-48c5-b1a8-90812915b8eb", "count": 0}, {"data": [{"userDefined": false, "text": "What classes are considered to be seminars?"}], "isTemplate": false, "id": "f9baefde-247a-43a1-b370-5a82a89feb4d", "count": 0}, {"data": [{"userDefined": false, "text": "What classes are considered to be seminars?"}], "isTemplate": false, "id": "66cdee49-dee8-4c92-b008-45b1fdff3793", "count": 0}, {"data": [{"userDefined": false, "text": "What classes are considered to be seminars?"}], "isTemplate": false, "id": "a171e15e-9bbd-44d6-ae1b-ccbdb86ab5ae", "count": 0}, {"data": [{"userDefined": false, "text": "What classes are considered to be seminars?"}], "isTemplate": false, "id": "22a6e67f-9d98-4982-8042-346fda3175fc", "count": 0}, {"data": [{"userDefined": false, "text": "What classes are considered to be seminars?"}], "isTemplate": false, "id": "7344c9a1-472c-4c63-9ee4-37e3e4d12c18", "count": 0}, {"data": [{"userDefined": false, "text": "What classes are considered to be seminars?"}], "isTemplate": false, "id": "2be7deb8-b5cc-4472-b973-678116845e80", "count": 0}, {"data": [{"userDefined": false, "text": "What classes are considered to be seminars?"}], "isTemplate": false, "id": "099d427f-8ca9-4ecc-bbe9-c09703950cfd", "count": 0}, {"data": [{"userDefined": false, "text": "What classes are considered to be seminars?"}], "isTemplate": false, "id": "5acc6689-ddf3-404b-abb0-e3ddb971e07d", "count": 0}, {"data": [{"userDefined": false, "text": "Which classes are taught as seminars?"}], "isTemplate": false, "id": "1dbfa312-b8a3-4694-b553-2acbea75b874", "count": 0}, {"data": [{"userDefined": false, "text": "Which classes are taught as seminars?"}], "isTemplate": false, "id": "b4f3a598-69c2-45ad-b394-f6643be826c9", "count": 0}, {"data": [{"userDefined": false, "text": "Which classes are taught as seminars?"}], "isTemplate": false, "id": "63bf25d1-0c6e-4f5d-8e95-f5caf9732146", "count": 0}, {"data": [{"userDefined": false, "text": "Which classes are taught as seminars?"}], "isTemplate": false, "id": "7114af06-6ac7-4e08-9cf2-04a3788330e2", "count": 0}, {"data": [{"userDefined": false, "text": "Which classes are taught as seminars?"}], "isTemplate": false, "id": "b2e88c2d-d50d-484a-86a5-a6fcc15114b5", "count": 0}, {"data": [{"userDefined": false, "text": "Which classes are taught as seminars?"}], "isTemplate": false, "id": "425bad98-47e0-4446-8b3b-c2d1734194e6", "count": 0}, {"data": [{"userDefined": false, "text": "Which classes are taught as seminars?"}], "isTemplate": false, "id": "6730a250-7b53-43b5-bef5-b96a2515cd4c", "count": 0}, {"data": [{"userDefined": false, "text": "Which classes are taught as seminars?"}], "isTemplate": false, "id": "bbb28cd3-aa0e-4025-b264-01b5fc02bba7", "count": 0}, {"data": [{"userDefined": false, "text": "Which classes are taught as seminars?"}], "isTemplate": false, "id": "8d2fc917-6f55-4a9e-9d2a-91e351b36c70", "count": 0}, {"data": [{"userDefined": false, "text": "Which classes are taught as seminars?"}], "isTemplate": false, "id": "1df02f76-1c2a-4c58-b909-5e852b1a1f87", "count": 0}, {"data": [{"userDefined": false, "text": "Which courses are taught like seminars?"}], "isTemplate": false, "id": "cf1321f9-eab6-4d20-aabd-b2249a1a775e", "count": 0}, {"data": [{"userDefined": false, "text": "Which courses are taught like seminars?"}], "isTemplate": false, "id": "c1e5b24c-15a3-49ff-8e95-6e75a0821d04", "count": 0}, {"data": [{"userDefined": false, "text": "Which courses are taught like seminars?"}], "isTemplate": false, "id": "3816bfbf-91bb-43e4-afc3-a73c7d106d71", "count": 0}, {"data": [{"userDefined": false, "text": "Which courses are taught like seminars?"}], "isTemplate": false, "id": "15864365-e61a-4e7f-a5b9-5050cf82668a", "count": 0}, {"data": [{"userDefined": false, "text": "Which courses are taught like seminars?"}], "isTemplate": false, "id": "b3a120d5-8175-491f-b2cf-c060587b925d", "count": 0}, {"data": [{"userDefined": false, "text": "Which courses are taught like seminars?"}], "isTemplate": false, "id": "fcb2c80c-e390-495f-a0da-d7baaa159ef9", "count": 0}, {"data": [{"userDefined": false, "text": "Which courses are taught like seminars?"}], "isTemplate": false, "id": "55417b2f-1dda-4672-aa44-c3ac81bc5d37", "count": 0}, {"data": [{"userDefined": false, "text": "Which courses are taught like seminars?"}], "isTemplate": false, "id": "b0410cfb-ed07-4160-967f-165736e9768a", "count": 0}, {"data": [{"userDefined": false, "text": "Which courses are taught like seminars?"}], "isTemplate": false, "id": "74501ae6-5d93-4a2c-93fc-03741f36f0a9", "count": 0}, {"data": [{"userDefined": false, "text": "Which courses are taught like seminars?"}], "isTemplate": false, "id": "b0b455c2-fb73-47cf-8e2f-18fade5e688e", "count": 0}, {"data": [{"userDefined": false, "text": "Which classes are seminars?"}], "isTemplate": false, "id": "1c2a180b-a53a-4bc7-9bfd-2dcff96dda41", "count": 0}, {"data": [{"userDefined": false, "text": "Which classes are seminars?"}], "isTemplate": false, "id": "ed5b0d14-00fa-48b7-b52b-e8d689d5c7a2", "count": 0}, {"data": [{"userDefined": false, "text": "Which classes are seminars?"}], "isTemplate": false, "id": "741c3c6f-8e06-4c02-9f99-aff47d829eba", "count": 0}, {"data": [{"userDefined": false, "text": "Which classes are seminars?"}], "isTemplate": false, "id": "0d230ce8-fbb8-41fa-9367-1eb6b21fce1b", "count": 0}, {"data": [{"userDefined": false, "text": "Which classes are seminars?"}], "isTemplate": false, "id": "66d125aa-0519-4641-840b-c84d9456e71a", "count": 0}, {"data": [{"userDefined": false, "text": "Which classes are seminars?"}], "isTemplate": false, "id": "5c5a96cc-f161-4130-86d7-08fcc8118f23", "count": 0}, {"data": [{"userDefined": false, "text": "Which classes are seminars?"}], "isTemplate": false, "id": "176642e3-eced-411f-ad34-7e5b2142cab8", "count": 0}, {"data": [{"userDefined": false, "text": "Which classes are seminars?"}], "isTemplate": false, "id": "49d5a406-8508-4308-ac99-9cdcbad48687", "count": 0}, {"data": [{"userDefined": false, "text": "Which classes are seminars?"}], "isTemplate": false, "id": "51f99ae9-b3c7-4ea5-8dc5-bd4839aaff6d", "count": 0}, {"data": [{"userDefined": false, "text": "Which classes are seminars?"}], "isTemplate": false, "id": "a7a32273-7d82-45dd-ab7c-751b5bfeb181", "count": 0}]