[{"id": "935d81fa-6c65-41c7-85d7-fdd31234bfdc", "data": [{"text": "Which classes satisfy GE Area ", "userDefined": false}, {"text": "A4", "userDefined": false, "alias": "GE_AREA", "meta": "@GE_AREA"}, {"text": "?", "userDefined": false}], "count": 0, "isTemplate": false}, {"id": "1adc6362-223c-4806-bdd5-740379a2747f", "data": [{"text": "Which classes satisfy GE Area ", "userDefined": false}, {"text": "D3", "userDefined": false, "alias": "GE_AREA", "meta": "@GE_AREA"}, {"text": "?", "userDefined": false}], "count": 0, "isTemplate": false}, {"id": "9be5b994-980e-45d0-b8aa-ff217687673b", "data": [{"text": "Which classes satisfy GE Area ", "userDefined": false}, {"text": "D4", "userDefined": false, "alias": "GE_AREA", "meta": "@GE_AREA"}, {"text": "?", "userDefined": false}], "count": 0, "isTemplate": false}, {"id": "6638a705-ede6-4c6e-af34-c8c3c12ec9ab", "data": [{"text": "Which classes satisfy GE Area ", "userDefined": false}, {"text": "b2", "userDefined": false, "alias": "GE_AREA", "meta": "@GE_AREA"}, {"text": "?", "userDefined": false}], "count": 0, "isTemplate": false}, {"id": "617a1748-3a54-4d2d-ba9f-365d91a4168e", "data": [{"text": "Which classes satisfy GE Area ", "userDefined": false}, {"text": "c2", "userDefined": false, "alias": "GE_AREA", "meta": "@GE_AREA"}, {"text": "?", "userDefined": false}], "count": 0, "isTemplate": false}, {"id": "0c15ef23-0c77-415b-a5bf-32335b097eac", "data": [{"text": "Which classes satisfy GE Area ", "userDefined": false}, {"text": "A2", "userDefined": false, "alias": "GE_AREA", "meta": "@GE_AREA"}, {"text": "?", "userDefined": false}], "count": 0, "isTemplate": false}, {"id": "71df0a85-724e-46b4-acec-bf34b70529d1", "data": [{"text": "Which classes satisfy GE Area ", "userDefined": false}, {"text": "b3", "userDefined": false, "alias": "GE_AREA", "meta": "@GE_AREA"}, {"text": "?", "userDefined": false}], "count": 0, "isTemplate": false}, {"id": "78f9aa6d-e976-4f2b-ba32-ca0511026c57", "data": [{"text": "Which classes satisfy GE Area ", "userDefined": false}, {"text": "c4", "userDefined": false, "alias": "GE_AREA", "meta": "@GE_AREA"}, {"text": "?", "userDefined": false}], "count": 0, "isTemplate": false}, {"id": "c534ed5e-0e4f-4f25-b8e5-3e96fdef260f", "data": [{"text": "Which classes satisfy GE Area ", "userDefined": false}, {"text": "d2", "userDefined": false, "alias": "GE_AREA", "meta": "@GE_AREA"}, {"text": "?", "userDefined": false}], "count": 0, "isTemplate": false}, {"id": "170443c4-364f-435a-833e-3160e0b230e1", "data": [{"text": "Which classes satisfy GE Area ", "userDefined": false}, {"text": "F", "userDefined": false, "alias": "GE_AREA", "meta": "@GE_AREA"}, {"text": "?", "userDefined": false}], "count": 0, "isTemplate": false}, {"id": "35e0e72f-e61b-4b43-ad8d-0ac43a3b606f", "data": [{"text": "Which courses satisfy GE Area ", "userDefined": false}, {"text": "c1", "userDefined": false, "alias": "GE_AREA", "meta": "@GE_AREA"}, {"text": "?", "userDefined": false}], "count": 0, "isTemplate": false}, {"id": "cc52000c-fe40-460e-8690-2d97e80071ad", "data": [{"text": "Which courses satisfy GE Area ", "userDefined": false}, {"text": "D2", "userDefined": false, "alias": "GE_AREA", "meta": "@GE_AREA"}, {"text": "?", "userDefined": false}], "count": 0, "isTemplate": false}, {"id": "988c9a78-a80f-478d-bce8-5111711aae22", "data": [{"text": "Which courses satisfy GE Area ", "userDefined": false}, {"text": "b3", "userDefined": false, "alias": "GE_AREA", "meta": "@GE_AREA"}, {"text": "?", "userDefined": false}], "count": 0, "isTemplate": false}, {"id": "19e68ddf-8e2c-4ba2-9537-165849481aa7", "data": [{"text": "Which courses satisfy GE Area ", "userDefined": false}, {"text": "c1", "userDefined": false, "alias": "GE_AREA", "meta": "@GE_AREA"}, {"text": "?", "userDefined": false}], "count": 0, "isTemplate": false}, {"id": "eddb9a9b-14ce-4e75-9337-8470263fa600", "data": [{"text": "Which courses satisfy GE Area ", "userDefined": false}, {"text": "C2", "userDefined": false, "alias": "GE_AREA", "meta": "@GE_AREA"}, {"text": "?", "userDefined": false}], "count": 0, "isTemplate": false}, {"id": "348359ef-5c43-4731-8936-b7729393a223", "data": [{"text": "Which courses satisfy GE Area ", "userDefined": false}, {"text": "F", "userDefined": false, "alias": "GE_AREA", "meta": "@GE_AREA"}, {"text": "?", "userDefined": false}], "count": 0, "isTemplate": false}, {"id": "f78e3a20-9644-49be-a634-11585748ae34", "data": [{"text": "Which courses satisfy GE Area ", "userDefined": false}, {"text": "b4", "userDefined": false, "alias": "GE_AREA", "meta": "@GE_AREA"}, {"text": "?", "userDefined": false}], "count": 0, "isTemplate": false}, {"id": "06fd2b19-0719-4dcd-af00-cc2518efc14a", "data": [{"text": "Which courses satisfy GE Area ", "userDefined": false}, {"text": "B4", "userDefined": false, "alias": "GE_AREA", "meta": "@GE_AREA"}, {"text": "?", "userDefined": false}], "count": 0, "isTemplate": false}, {"id": "584c5c2f-8f4d-46af-b22c-1460ff5be101", "data": [{"text": "Which courses satisfy GE Area ", "userDefined": false}, {"text": "C1", "userDefined": false, "alias": "GE_AREA", "meta": "@GE_AREA"}, {"text": "?", "userDefined": false}], "count": 0, "isTemplate": false}, {"id": "218c0720-96a1-4f8d-b931-8b611e31add9", "data": [{"text": "Which courses satisfy GE Area ", "userDefined": false}, {"text": "C3", "userDefined": false, "alias": "GE_AREA", "meta": "@GE_AREA"}, {"text": "?", "userDefined": false}], "count": 0, "isTemplate": false}, {"id": "299da825-9062-4d03-a23b-c6d0c90c9480", "data": [{"text": "Which classes can I satisfy my ", "userDefined": false}, {"text": "b2", "userDefined": false, "alias": "GE_AREA", "meta": "@GE_AREA"}, {"text": " with?", "userDefined": false}], "count": 0, "isTemplate": false}, {"id": "3528fe0e-a355-4040-9526-093fbc96fe7d", "data": [{"text": "Which classes can I satisfy my ", "userDefined": false}, {"text": "b3", "userDefined": false, "alias": "GE_AREA", "meta": "@GE_AREA"}, {"text": " with?", "userDefined": false}], "count": 0, "isTemplate": false}, {"id": "c9fff6d3-9ffb-46fc-b2cb-5f834f395e61", "data": [{"text": "Which classes can I satisfy my ", "userDefined": false}, {"text": "a1", "userDefined": false, "alias": "GE_AREA", "meta": "@GE_AREA"}, {"text": " with?", "userDefined": false}], "count": 0, "isTemplate": false}, {"id": "40934e42-d2be-4011-ab14-351b4d7b5c0d", "data": [{"text": "Which classes can I satisfy my ", "userDefined": false}, {"text": "A4", "userDefined": false, "alias": "GE_AREA", "meta": "@GE_AREA"}, {"text": " with?", "userDefined": false}], "count": 0, "isTemplate": false}, {"id": "498a36c0-8b78-4dbf-86ec-c18c2fdd022e", "data": [{"text": "Which classes can I satisfy my ", "userDefined": false}, {"text": "b1", "userDefined": false, "alias": "GE_AREA", "meta": "@GE_AREA"}, {"text": " with?", "userDefined": false}], "count": 0, "isTemplate": false}, {"id": "f6ccf20a-d15f-4b54-b0d4-f01beb910eb3", "data": [{"text": "Which classes can I satisfy my ", "userDefined": false}, {"text": "D3", "userDefined": false, "alias": "GE_AREA", "meta": "@GE_AREA"}, {"text": " with?", "userDefined": false}], "count": 0, "isTemplate": false}, {"id": "3ca75284-d496-478e-b190-92b391917565", "data": [{"text": "Which classes can I satisfy my ", "userDefined": false}, {"text": "B2", "userDefined": false, "alias": "GE_AREA", "meta": "@GE_AREA"}, {"text": " with?", "userDefined": false}], "count": 0, "isTemplate": false}, {"id": "ad66e1f1-ed83-43ed-8e24-e576bc767620", "data": [{"text": "Which classes can I satisfy my ", "userDefined": false}, {"text": "b7", "userDefined": false, "alias": "GE_AREA", "meta": "@GE_AREA"}, {"text": " with?", "userDefined": false}], "count": 0, "isTemplate": false}, {"id": "3abb1968-2db2-4f61-be69-eec18e047c77", "data": [{"text": "Which classes can I satisfy my ", "userDefined": false}, {"text": "b2", "userDefined": false, "alias": "GE_AREA", "meta": "@GE_AREA"}, {"text": " with?", "userDefined": false}], "count": 0, "isTemplate": false}, {"id": "3180d543-2b05-46e6-b382-3117ac41c1e3", "data": [{"text": "Which classes can I satisfy my ", "userDefined": false}, {"text": "D1", "userDefined": false, "alias": "GE_AREA", "meta": "@GE_AREA"}, {"text": " with?", "userDefined": false}], "count": 0, "isTemplate": false}, {"id": "2f43cef0-56ad-4c6c-99ad-14a7411ca872", "data": [{"text": "Which courses fulfill GE Area ", "userDefined": false}, {"text": "C1", "userDefined": false, "alias": "GE_AREA", "meta": "@GE_AREA"}, {"text": "?", "userDefined": false}], "count": 0, "isTemplate": false}, {"id": "9287f219-aba0-4ffb-a85d-268e5e033679", "data": [{"text": "Which courses fulfill GE Area ", "userDefined": false}, {"text": "c2", "userDefined": false, "alias": "GE_AREA", "meta": "@GE_AREA"}, {"text": "?", "userDefined": false}], "count": 0, "isTemplate": false}, {"id": "994c7034-2d35-4364-b60e-d921f9a47fa7", "data": [{"text": "Which courses fulfill GE Area ", "userDefined": false}, {"text": "a3", "userDefined": false, "alias": "GE_AREA", "meta": "@GE_AREA"}, {"text": "?", "userDefined": false}], "count": 0, "isTemplate": false}, {"id": "239f1418-4610-4733-a350-9adaffae2685", "data": [{"text": "Which courses fulfill GE Area ", "userDefined": false}, {"text": "A4", "userDefined": false, "alias": "GE_AREA", "meta": "@GE_AREA"}, {"text": "?", "userDefined": false}], "count": 0, "isTemplate": false}, {"id": "46d08281-efb9-42f4-bca4-9a640ab72a55", "data": [{"text": "Which courses fulfill GE Area ", "userDefined": false}, {"text": "C1", "userDefined": false, "alias": "GE_AREA", "meta": "@GE_AREA"}, {"text": "?", "userDefined": false}], "count": 0, "isTemplate": false}, {"id": "8889b6d2-d902-453c-b057-5f4b713f6443", "data": [{"text": "Which courses fulfill GE Area ", "userDefined": false}, {"text": "A4", "userDefined": false, "alias": "GE_AREA", "meta": "@GE_AREA"}, {"text": "?", "userDefined": false}], "count": 0, "isTemplate": false}, {"id": "5fd664b9-df63-45da-8132-88389477824c", "data": [{"text": "Which courses fulfill GE Area ", "userDefined": false}, {"text": "b3", "userDefined": false, "alias": "GE_AREA", "meta": "@GE_AREA"}, {"text": "?", "userDefined": false}], "count": 0, "isTemplate": false}, {"id": "34f9b602-7898-4cf0-9f58-21ad0795ac6f", "data": [{"text": "Which courses fulfill GE Area ", "userDefined": false}, {"text": "a3", "userDefined": false, "alias": "GE_AREA", "meta": "@GE_AREA"}, {"text": "?", "userDefined": false}], "count": 0, "isTemplate": false}, {"id": "e0c2da13-0d0e-4cd7-9924-774eedb02ec6", "data": [{"text": "Which courses fulfill GE Area ", "userDefined": false}, {"text": "D4", "userDefined": false, "alias": "GE_AREA", "meta": "@GE_AREA"}, {"text": "?", "userDefined": false}], "count": 0, "isTemplate": false}, {"id": "6113aea5-71b5-4b6b-8c75-ccf65d80101d", "data": [{"text": "Which courses fulfill GE Area ", "userDefined": false}, {"text": "a4", "userDefined": false, "alias": "GE_AREA", "meta": "@GE_AREA"}, {"text": "?", "userDefined": false}], "count": 0, "isTemplate": false}, {"id": "3e87ce5f-248b-4a48-90d5-4e0fa937ed69", "data": [{"text": "Which classes can I fulfill my ", "userDefined": false}, {"text": "b4", "userDefined": false, "alias": "GE_AREA", "meta": "@GE_AREA"}, {"text": " with?", "userDefined": false}], "count": 0, "isTemplate": false}, {"id": "7703f83e-9cba-4b15-ae5a-4510f8547fe8", "data": [{"text": "Which classes can I fulfill my ", "userDefined": false}, {"text": "a3", "userDefined": false, "alias": "GE_AREA", "meta": "@GE_AREA"}, {"text": " with?", "userDefined": false}], "count": 0, "isTemplate": false}, {"id": "0aa89d26-3063-43b3-82c4-c7cc44f8e747", "data": [{"text": "Which classes can I fulfill my ", "userDefined": false}, {"text": "A4", "userDefined": false, "alias": "GE_AREA", "meta": "@GE_AREA"}, {"text": " with?", "userDefined": false}], "count": 0, "isTemplate": false}, {"id": "365cb0ee-14df-43a3-9cdd-183e8b365059", "data": [{"text": "Which classes can I fulfill my ", "userDefined": false}, {"text": "C2", "userDefined": false, "alias": "GE_AREA", "meta": "@GE_AREA"}, {"text": " with?", "userDefined": false}], "count": 0, "isTemplate": false}, {"id": "b11fd3d6-3903-410d-8825-4c7ad65be8d9", "data": [{"text": "Which classes can I fulfill my ", "userDefined": false}, {"text": "C1", "userDefined": false, "alias": "GE_AREA", "meta": "@GE_AREA"}, {"text": " with?", "userDefined": false}], "count": 0, "isTemplate": false}, {"id": "37d284ea-4cc9-49db-8431-43b62f11e49b", "data": [{"text": "Which classes can I fulfill my ", "userDefined": false}, {"text": "F", "userDefined": false, "alias": "GE_AREA", "meta": "@GE_AREA"}, {"text": " with?", "userDefined": false}], "count": 0, "isTemplate": false}, {"id": "c70175cd-69fc-4054-839b-720f160e0ff5", "data": [{"text": "Which classes can I fulfill my ", "userDefined": false}, {"text": "d1", "userDefined": false, "alias": "GE_AREA", "meta": "@GE_AREA"}, {"text": " with?", "userDefined": false}], "count": 0, "isTemplate": false}, {"id": "126bb812-e32d-418a-8d13-29c5998e9a47", "data": [{"text": "Which classes can I fulfill my ", "userDefined": false}, {"text": "c3", "userDefined": false, "alias": "GE_AREA", "meta": "@GE_AREA"}, {"text": " with?", "userDefined": false}], "count": 0, "isTemplate": false}, {"id": "8e162e21-39fa-4699-a9e4-b1ccb2e0eed7", "data": [{"text": "Which classes can I fulfill my ", "userDefined": false}, {"text": "A2", "userDefined": false, "alias": "GE_AREA", "meta": "@GE_AREA"}, {"text": " with?", "userDefined": false}], "count": 0, "isTemplate": false}, {"id": "9471f129-f625-42a1-931a-1e5b61a67850", "data": [{"text": "Which classes can I fulfill my ", "userDefined": false}, {"text": "D3", "userDefined": false, "alias": "GE_AREA", "meta": "@GE_AREA"}, {"text": " with?", "userDefined": false}], "count": 0, "isTemplate": false}, {"id": "b6864403-a115-427f-ac14-aed6fe7f060b", "data": [{"text": "Which classes can I get credits for GE Area ", "userDefined": false}, {"text": "b2", "userDefined": false, "alias": "GE_AREA", "meta": "@GE_AREA"}, {"text": " with?", "userDefined": false}], "count": 0, "isTemplate": false}, {"id": "e35dd0e9-b018-4b5f-ac94-bbc04e6553c9", "data": [{"text": "Which classes can I get credits for GE Area ", "userDefined": false}, {"text": "c3", "userDefined": false, "alias": "GE_AREA", "meta": "@GE_AREA"}, {"text": " with?", "userDefined": false}], "count": 0, "isTemplate": false}, {"id": "5e4de3ee-8603-4b3c-bc37-5cf96d2ea22a", "data": [{"text": "Which classes can I get credits for GE Area ", "userDefined": false}, {"text": "f", "userDefined": false, "alias": "GE_AREA", "meta": "@GE_AREA"}, {"text": " with?", "userDefined": false}], "count": 0, "isTemplate": false}, {"id": "0ca2947b-da09-4349-80f8-099f1c19ac32", "data": [{"text": "Which classes can I get credits for GE Area ", "userDefined": false}, {"text": "F", "userDefined": false, "alias": "GE_AREA", "meta": "@GE_AREA"}, {"text": " with?", "userDefined": false}], "count": 0, "isTemplate": false}, {"id": "037018d5-1b02-4be4-803e-284c4f772383", "data": [{"text": "Which classes can I get credits for GE Area ", "userDefined": false}, {"text": "A3", "userDefined": false, "alias": "GE_AREA", "meta": "@GE_AREA"}, {"text": " with?", "userDefined": false}], "count": 0, "isTemplate": false}, {"id": "76621bc1-52c9-4dc2-8377-a3a7aed60a6d", "data": [{"text": "Which classes can I get credits for GE Area ", "userDefined": false}, {"text": "a3", "userDefined": false, "alias": "GE_AREA", "meta": "@GE_AREA"}, {"text": " with?", "userDefined": false}], "count": 0, "isTemplate": false}, {"id": "bf368b03-3738-4ec9-924d-6d5f96870636", "data": [{"text": "Which classes can I get credits for GE Area ", "userDefined": false}, {"text": "C3", "userDefined": false, "alias": "GE_AREA", "meta": "@GE_AREA"}, {"text": " with?", "userDefined": false}], "count": 0, "isTemplate": false}, {"id": "b7be3ba5-3c62-4254-9c46-5a472c1b5203", "data": [{"text": "Which classes can I get credits for GE Area ", "userDefined": false}, {"text": "c4", "userDefined": false, "alias": "GE_AREA", "meta": "@GE_AREA"}, {"text": " with?", "userDefined": false}], "count": 0, "isTemplate": false}, {"id": "b558626f-dadd-4446-84d4-f1e5e16a8ce7", "data": [{"text": "Which classes can I get credits for GE Area ", "userDefined": false}, {"text": "a3", "userDefined": false, "alias": "GE_AREA", "meta": "@GE_AREA"}, {"text": " with?", "userDefined": false}], "count": 0, "isTemplate": false}, {"id": "b0f78e13-4126-40e7-92a3-4261ebb8eded", "data": [{"text": "Which classes can I get credits for GE Area ", "userDefined": false}, {"text": "d1", "userDefined": false, "alias": "GE_AREA", "meta": "@GE_AREA"}, {"text": " with?", "userDefined": false}], "count": 0, "isTemplate": false}, {"id": "f1d2de36-3e3b-4d41-b73e-4bb2c9675779", "data": [{"text": "Which classes give me credits for ", "userDefined": false}, {"text": "a1", "userDefined": false, "alias": "GE_AREA", "meta": "@GE_AREA"}, {"text": "?", "userDefined": false}], "count": 0, "isTemplate": false}, {"id": "b834a28a-389a-4391-bc98-d4620ba748a4", "data": [{"text": "Which classes give me credits for ", "userDefined": false}, {"text": "a2", "userDefined": false, "alias": "GE_AREA", "meta": "@GE_AREA"}, {"text": "?", "userDefined": false}], "count": 0, "isTemplate": false}, {"id": "2e168629-6646-4b5f-a7b8-ff408471bbf0", "data": [{"text": "Which classes give me credits for ", "userDefined": false}, {"text": "A2", "userDefined": false, "alias": "GE_AREA", "meta": "@GE_AREA"}, {"text": "?", "userDefined": false}], "count": 0, "isTemplate": false}, {"id": "c93ef17d-5370-4fdc-a02a-dbd3a4e07b01", "data": [{"text": "Which classes give me credits for ", "userDefined": false}, {"text": "D1", "userDefined": false, "alias": "GE_AREA", "meta": "@GE_AREA"}, {"text": "?", "userDefined": false}], "count": 0, "isTemplate": false}, {"id": "105e9401-867c-4233-87d1-76392ac70c2f", "data": [{"text": "Which classes give me credits for ", "userDefined": false}, {"text": "a1", "userDefined": false, "alias": "GE_AREA", "meta": "@GE_AREA"}, {"text": "?", "userDefined": false}], "count": 0, "isTemplate": false}, {"id": "4ac86f67-b9e7-4a51-a52a-4a99f601205f", "data": [{"text": "Which classes give me credits for ", "userDefined": false}, {"text": "B2", "userDefined": false, "alias": "GE_AREA", "meta": "@GE_AREA"}, {"text": "?", "userDefined": false}], "count": 0, "isTemplate": false}, {"id": "3d544a91-6d4d-49c5-98cf-baa6cea1b451", "data": [{"text": "Which classes give me credits for ", "userDefined": false}, {"text": "C1", "userDefined": false, "alias": "GE_AREA", "meta": "@GE_AREA"}, {"text": "?", "userDefined": false}], "count": 0, "isTemplate": false}, {"id": "c0abd6df-d36b-448e-bf6a-f75419105ac1", "data": [{"text": "Which classes give me credits for ", "userDefined": false}, {"text": "A2", "userDefined": false, "alias": "GE_AREA", "meta": "@GE_AREA"}, {"text": "?", "userDefined": false}], "count": 0, "isTemplate": false}, {"id": "f8db5ec6-2b06-4e17-a837-e8333c278fad", "data": [{"text": "Which classes give me credits for ", "userDefined": false}, {"text": "D3", "userDefined": false, "alias": "GE_AREA", "meta": "@GE_AREA"}, {"text": "?", "userDefined": false}], "count": 0, "isTemplate": false}, {"id": "cb5c5c7d-dbed-4c0d-85e9-2be735743a11", "data": [{"text": "Which classes give me credits for ", "userDefined": false}, {"text": "A3", "userDefined": false, "alias": "GE_AREA", "meta": "@GE_AREA"}, {"text": "?", "userDefined": false}], "count": 0, "isTemplate": false}, {"id": "9f764133-185b-4735-b90e-8f8d2a7d8073", "data": [{"text": "Which classes are possible to get credits for GE Area ", "userDefined": false}, {"text": "c2", "userDefined": false, "alias": "GE_AREA", "meta": "@GE_AREA"}, {"text": "?", "userDefined": false}], "count": 0, "isTemplate": false}, {"id": "6c2c6128-cd9b-4462-a0bd-4fea9a4a034e", "data": [{"text": "Which classes are possible to get credits for GE Area ", "userDefined": false}, {"text": "b3", "userDefined": false, "alias": "GE_AREA", "meta": "@GE_AREA"}, {"text": "?", "userDefined": false}], "count": 0, "isTemplate": false}, {"id": "d906a7d7-ead9-412f-a4fa-3a5bdf6ace87", "data": [{"text": "Which classes are possible to get credits for GE Area ", "userDefined": false}, {"text": "c3", "userDefined": false, "alias": "GE_AREA", "meta": "@GE_AREA"}, {"text": "?", "userDefined": false}], "count": 0, "isTemplate": false}, {"id": "0a51a805-9b4c-4d4a-bbf4-e92e77067880", "data": [{"text": "Which classes are possible to get credits for GE Area ", "userDefined": false}, {"text": "C1", "userDefined": false, "alias": "GE_AREA", "meta": "@GE_AREA"}, {"text": "?", "userDefined": false}], "count": 0, "isTemplate": false}, {"id": "cb379078-d924-466f-ba90-d7749f6e712d", "data": [{"text": "Which classes are possible to get credits for GE Area ", "userDefined": false}, {"text": "a3", "userDefined": false, "alias": "GE_AREA", "meta": "@GE_AREA"}, {"text": "?", "userDefined": false}], "count": 0, "isTemplate": false}, {"id": "e8e408d6-b2f0-411c-9494-3816ae5590e3", "data": [{"text": "Which classes are possible to get credits for GE Area ", "userDefined": false}, {"text": "C4", "userDefined": false, "alias": "GE_AREA", "meta": "@GE_AREA"}, {"text": "?", "userDefined": false}], "count": 0, "isTemplate": false}, {"id": "82d0e753-b970-4919-a34c-307d9ba8bcb7", "data": [{"text": "Which classes are possible to get credits for GE Area ", "userDefined": false}, {"text": "b4", "userDefined": false, "alias": "GE_AREA", "meta": "@GE_AREA"}, {"text": "?", "userDefined": false}], "count": 0, "isTemplate": false}, {"id": "30092f09-dc1d-406f-b205-901eeb2ab995", "data": [{"text": "Which classes are possible to get credits for GE Area ", "userDefined": false}, {"text": "f", "userDefined": false, "alias": "GE_AREA", "meta": "@GE_AREA"}, {"text": "?", "userDefined": false}], "count": 0, "isTemplate": false}, {"id": "472d35cf-18b9-4ddb-a5a3-443b0980f513", "data": [{"text": "Which classes are possible to get credits for GE Area ", "userDefined": false}, {"text": "B4", "userDefined": false, "alias": "GE_AREA", "meta": "@GE_AREA"}, {"text": "?", "userDefined": false}], "count": 0, "isTemplate": false}, {"id": "3e69e72e-cc65-45d6-8063-e8eda806514c", "data": [{"text": "Which classes are possible to get credits for GE Area ", "userDefined": false}, {"text": "a4", "userDefined": false, "alias": "GE_AREA", "meta": "@GE_AREA"}, {"text": "?", "userDefined": false}], "count": 0, "isTemplate": false}, {"id": "cb23ac1c-f82f-41dd-aeca-ca7acb8995b9", "data": [{"text": "What can I take to fulfill GE ", "userDefined": false}, {"text": "C1", "userDefined": false, "alias": "GE_AREA", "meta": "@GE_AREA"}, {"text": "?", "userDefined": false}], "count": 0, "isTemplate": false}, {"id": "34d96cc9-4719-420c-b02a-87d0145dba9f", "data": [{"text": "What can I take to fulfill GE ", "userDefined": false}, {"text": "d4", "userDefined": false, "alias": "GE_AREA", "meta": "@GE_AREA"}, {"text": "?", "userDefined": false}], "count": 0, "isTemplate": false}, {"id": "050138d6-1d5a-4d72-bb45-2d4ab90b06db", "data": [{"text": "What can I take to fulfill GE ", "userDefined": false}, {"text": "B2", "userDefined": false, "alias": "GE_AREA", "meta": "@GE_AREA"}, {"text": "?", "userDefined": false}], "count": 0, "isTemplate": false}, {"id": "f1b157f9-2279-4809-bd31-b6a612b56eef", "data": [{"text": "What can I take to fulfill GE ", "userDefined": false}, {"text": "F", "userDefined": false, "alias": "GE_AREA", "meta": "@GE_AREA"}, {"text": "?", "userDefined": false}], "count": 0, "isTemplate": false}, {"id": "aa884e7e-b6d8-4957-8577-e7be98269274", "data": [{"text": "What can I take to fulfill GE ", "userDefined": false}, {"text": "d3", "userDefined": false, "alias": "GE_AREA", "meta": "@GE_AREA"}, {"text": "?", "userDefined": false}], "count": 0, "isTemplate": false}, {"id": "3ebca43f-4f66-4420-85fd-e5a984f40458", "data": [{"text": "What can I take to fulfill GE ", "userDefined": false}, {"text": "B2", "userDefined": false, "alias": "GE_AREA", "meta": "@GE_AREA"}, {"text": "?", "userDefined": false}], "count": 0, "isTemplate": false}, {"id": "f7f55165-395d-4ec5-96f7-20d0507d5f98", "data": [{"text": "What can I take to fulfill GE ", "userDefined": false}, {"text": "b7", "userDefined": false, "alias": "GE_AREA", "meta": "@GE_AREA"}, {"text": "?", "userDefined": false}], "count": 0, "isTemplate": false}, {"id": "45fafac7-f8fc-4a3d-9f37-b6f782d91e56", "data": [{"text": "What can I take to fulfill GE ", "userDefined": false}, {"text": "C2", "userDefined": false, "alias": "GE_AREA", "meta": "@GE_AREA"}, {"text": "?", "userDefined": false}], "count": 0, "isTemplate": false}, {"id": "80b4b75a-278a-49ab-ba11-c98e2a3313c6", "data": [{"text": "What can I take to fulfill GE ", "userDefined": false}, {"text": "D4", "userDefined": false, "alias": "GE_AREA", "meta": "@GE_AREA"}, {"text": "?", "userDefined": false}], "count": 0, "isTemplate": false}, {"id": "99420142-a2f9-429c-b70c-a200f87d4fb6", "data": [{"text": "What can I take to fulfill GE ", "userDefined": false}, {"text": "D3", "userDefined": false, "alias": "GE_AREA", "meta": "@GE_AREA"}, {"text": "?", "userDefined": false}], "count": 0, "isTemplate": false}, {"id": "c231b13d-ff1b-42dd-824b-2fb728c71151", "data": [{"text": "What can I take to fulfill my ", "userDefined": false}, {"text": "d1", "userDefined": false, "alias": "GE_AREA", "meta": "@GE_AREA"}, {"text": "?", "userDefined": false}], "count": 0, "isTemplate": false}, {"id": "6e946db8-1f68-4fb5-89c7-be9c80844032", "data": [{"text": "What can I take to fulfill my ", "userDefined": false}, {"text": "D2", "userDefined": false, "alias": "GE_AREA", "meta": "@GE_AREA"}, {"text": "?", "userDefined": false}], "count": 0, "isTemplate": false}, {"id": "b61a7dce-a709-432a-8f1b-25ebb61a8832", "data": [{"text": "What can I take to fulfill my ", "userDefined": false}, {"text": "a4", "userDefined": false, "alias": "GE_AREA", "meta": "@GE_AREA"}, {"text": "?", "userDefined": false}], "count": 0, "isTemplate": false}, {"id": "111ac48f-51bb-4664-868b-bb40ecbbc208", "data": [{"text": "What can I take to fulfill my ", "userDefined": false}, {"text": "B4", "userDefined": false, "alias": "GE_AREA", "meta": "@GE_AREA"}, {"text": "?", "userDefined": false}], "count": 0, "isTemplate": false}, {"id": "89cc17fe-4a3d-40b1-9f10-ce0e64ad0b10", "data": [{"text": "What can I take to fulfill my ", "userDefined": false}, {"text": "a4", "userDefined": false, "alias": "GE_AREA", "meta": "@GE_AREA"}, {"text": "?", "userDefined": false}], "count": 0, "isTemplate": false}, {"id": "a8ff13cf-cedd-4102-b198-6f65594317a5", "data": [{"text": "What can I take to fulfill my ", "userDefined": false}, {"text": "C4", "userDefined": false, "alias": "GE_AREA", "meta": "@GE_AREA"}, {"text": "?", "userDefined": false}], "count": 0, "isTemplate": false}, {"id": "afdfcf74-1d24-4f84-a30b-9c3cd5494345", "data": [{"text": "What can I take to fulfill my ", "userDefined": false}, {"text": "a3", "userDefined": false, "alias": "GE_AREA", "meta": "@GE_AREA"}, {"text": "?", "userDefined": false}], "count": 0, "isTemplate": false}, {"id": "e180c2ab-b5ee-497c-b70d-c68ff5c6c85b", "data": [{"text": "What can I take to fulfill my ", "userDefined": false}, {"text": "F", "userDefined": false, "alias": "GE_AREA", "meta": "@GE_AREA"}, {"text": "?", "userDefined": false}], "count": 0, "isTemplate": false}, {"id": "4d27eb4e-5217-4fa3-bf30-b4935ffb5fb9", "data": [{"text": "What can I take to fulfill my ", "userDefined": false}, {"text": "C2", "userDefined": false, "alias": "GE_AREA", "meta": "@GE_AREA"}, {"text": "?", "userDefined": false}], "count": 0, "isTemplate": false}, {"id": "9ff6f94f-dd4c-4b9d-bd5d-b1ea4bcc49a6", "data": [{"text": "What can I take to fulfill my ", "userDefined": false}, {"text": "D4", "userDefined": false, "alias": "GE_AREA", "meta": "@GE_AREA"}, {"text": "?", "userDefined": false}], "count": 0, "isTemplate": false}, {"id": "6afb80aa-5e9f-41e0-b1e6-e7eb202651db", "data": [{"text": "Which classes fulfill GE Area ", "userDefined": false}, {"text": "c3", "userDefined": false, "alias": "GE_AREA", "meta": "@GE_AREA"}, {"text": "?", "userDefined": false}], "count": 0, "isTemplate": false}, {"id": "e268361e-ce37-4a57-b68c-d2928efdb6b5", "data": [{"text": "Which classes fulfill GE Area ", "userDefined": false}, {"text": "d2", "userDefined": false, "alias": "GE_AREA", "meta": "@GE_AREA"}, {"text": "?", "userDefined": false}], "count": 0, "isTemplate": false}, {"id": "0925b6c5-4ed4-4b65-9a0a-1f9bd7242187", "data": [{"text": "Which classes fulfill GE Area ", "userDefined": false}, {"text": "b7", "userDefined": false, "alias": "GE_AREA", "meta": "@GE_AREA"}, {"text": "?", "userDefined": false}], "count": 0, "isTemplate": false}, {"id": "3bdd80c3-6be9-4453-9c91-8ab22724df58", "data": [{"text": "Which classes fulfill GE Area ", "userDefined": false}, {"text": "c2", "userDefined": false, "alias": "GE_AREA", "meta": "@GE_AREA"}, {"text": "?", "userDefined": false}], "count": 0, "isTemplate": false}, {"id": "b0c72726-65e7-4978-b2f0-8f36af5ce176", "data": [{"text": "Which classes fulfill GE Area ", "userDefined": false}, {"text": "D3", "userDefined": false, "alias": "GE_AREA", "meta": "@GE_AREA"}, {"text": "?", "userDefined": false}], "count": 0, "isTemplate": false}, {"id": "6e959806-0d25-45ec-a7e6-84f207a28524", "data": [{"text": "Which classes fulfill GE Area ", "userDefined": false}, {"text": "A1", "userDefined": false, "alias": "GE_AREA", "meta": "@GE_AREA"}, {"text": "?", "userDefined": false}], "count": 0, "isTemplate": false}, {"id": "1e202621-5296-45d4-b0df-ef12827d378a", "data": [{"text": "Which classes fulfill GE Area ", "userDefined": false}, {"text": "A2", "userDefined": false, "alias": "GE_AREA", "meta": "@GE_AREA"}, {"text": "?", "userDefined": false}], "count": 0, "isTemplate": false}, {"id": "9ee4a5e5-de9b-4afa-b91b-df6662380cd9", "data": [{"text": "Which classes fulfill GE Area ", "userDefined": false}, {"text": "d4", "userDefined": false, "alias": "GE_AREA", "meta": "@GE_AREA"}, {"text": "?", "userDefined": false}], "count": 0, "isTemplate": false}, {"id": "b1fe1387-6289-429d-bf17-614c3fe114d3", "data": [{"text": "Which classes fulfill GE Area ", "userDefined": false}, {"text": "B3", "userDefined": false, "alias": "GE_AREA", "meta": "@GE_AREA"}, {"text": "?", "userDefined": false}], "count": 0, "isTemplate": false}, {"id": "58d5126b-1cea-43a7-9584-67c124a874e9", "data": [{"text": "Which classes fulfill GE Area ", "userDefined": false}, {"text": "D1", "userDefined": false, "alias": "GE_AREA", "meta": "@GE_AREA"}, {"text": "?", "userDefined": false}], "count": 0, "isTemplate": false}]